letterwise_stt/__init__.py
letterwise_stt/main.py
letterwise_stt/stt_phoneme_extractor.py
letterwise_stt/utils.py
letterwise_stt/word_reconstructor.py
letterwise_stt/data/__init__.py
letterwise_stt/data/words_alpha.txt
letterwise_stt-0.6.dist-info/METADATA
letterwise_stt-0.6.dist-info/WHEEL
letterwise_stt-0.6.dist-info/entry_points.txt
letterwise_stt-0.6.dist-info/top_level.txt
letterwise_stt-0.6.dist-info/RECORD
