Metadata-Version: 2.4
Name: letterwise_stt
Version: 0.6
Summary: Phoneme-level Speech-to-Text with AI reconstruction
Author: AmongTheCouch Studios
Author-email: jack-the-gamer@hotmail.com
Classifier: Programming Language :: Python :: 3
Classifier: Operating System :: OS Independent
Requires-Python: >=3.8
Requires-Dist: vosk
Requires-Dist: soundfile
Requires-Dist: transformers
Requires-Dist: torch
Requires-Dist: pyaudio
Requires-Dist: sounddevice
Dynamic: author
Dynamic: author-email
Dynamic: classifier
Dynamic: requires-dist
Dynamic: requires-python
Dynamic: summary
